diligence_service/__init__.py
diligence_service/api/__init__.py
diligence_service/api/due_diligences/__init__.py
diligence_service/api/due_diligences/get_due_diligence.py
diligence_service/api/projects/__init__.py
diligence_service/api/projects/get_project.py
diligence_service/client.py
diligence_service/errors.py
diligence_service/models/__init__.py
diligence_service/models/due_diligence.py
diligence_service/models/http_validation_error.py
diligence_service/models/project.py
diligence_service/models/validation_error.py
diligence_service/py.typed
diligence_service/types.py
diligence_service-1.0.8.dist-info/METADATA
diligence_service-1.0.8.dist-info/WHEEL
diligence_service-1.0.8.dist-info/RECORD
